rocoda/augments/__init__.py
rocoda/augments/causal.py
rocoda/augments/causal_online.py
rocoda/augments/equivariant.py
rocoda/augments/visual.py
rocoda/data/__init__.py
rocoda/data/prep.py
rocoda/environments/__init__.py
rocoda/environments/base.py
rocoda/environments/issacsim.py
rocoda/environments/robosuite.py
rocoda-0.1.1.dist-info/licenses/LICENSE
rocoda-0.1.1.dist-info/METADATA
rocoda-0.1.1.dist-info/WHEEL
rocoda-0.1.1.dist-info/top_level.txt
rocoda-0.1.1.dist-info/RECORD
