Metadata-Version: 2.4
Name: rocoda
Version: 0.1.1
Summary: RoCoDA Alpha 0.1
Author: GT PAIR Lab
License: MIT
Requires-Python: >=3.10
License-File: LICENSE
Requires-Dist: h5py>=3.13.0
Requires-Dist: jupyter>=1.1.1
Requires-Dist: networkx>=3.4.2
Requires-Dist: pillow>=11.2.1
Requires-Dist: robosuite==1.4.1
Requires-Dist: torch==2.6.0
Requires-Dist: torchvision>=0.21.0
Requires-Dist: tqdm>=4.67.1
Dynamic: license-file
